boon/__init__.py
boon/boon.py
boon-0.1.0.dist-info/METADATA
boon-0.1.0.dist-info/RECORD
boon-0.1.0.dist-info/WHEEL
boon-0.1.0.dist-info/top_level.txt
