Metadata-Version: 2.1
Name: boon
Version: 0.1.0
Summary: Functions to estimate the expected best-out-of-n result from a set of validation and test results.
Home-page: https://gitlab.com/obajgar/boon/
Author: Ondrej Bajgar
Author-email: OBajgar@cz.ibm.com
License: Apache-2.0
Platform: UNKNOWN
Classifier: Programming Language :: Python
Classifier: Operating System :: OS Independent
Requires-Dist: numpy
